{
    "id": "tricube",
    "title": "Tricube Tales",
    "description": "Game System for Tricube Tales. (And now Tricube Tactics)",
    "version": "2.13.0",
    "authors": [
      {
        "name": "ParvusDomus",
        "flags": {}
      }
    ],
    "compatibility": {
      "minimum": "13",
      "verified": "13"
    },
    "esmodules": [
      "tricube.js"
    ],
    "styles": [
      "style/tricube.css"
    ],
    "media": [
      {
        "type": "setup",
        "url": "systems/tricube/style/images/TT_Logo2.png",
        "thumbnail": "systems/tricube/style/images/TT_Logo2.png"
      }
    ],
    "relationships": {
    "requires": [{
      "id": "color-picker",
      "type": "module",
      "manifest": "https://github.com/Larkinabout/fvtt-color-picker/releases/latest/download/module.json",
      "compatibility": {
        "minimum" : "1.6",
        "verified": "1.6"
      }
    }]
    },

    "languages": [
      {
        "lang": "es",
        "name": "Spanish",
        "path": "lang/es.json",
        "flags": {}
      },
      {
        "lang": "en",
        "name": "English",
        "path": "lang/en.json",
        "flags": {}
      }
    ],
    "initiative": "@initiative",
    "grid": {
      "distance": 2,
      "units": "m"
    },
    "primaryTokenAttribute": "resources.resolve",
    "secondaryTokenAttribute": "resources.karma",
    "url": "https://github.com/parvusdomus/tricube",
    "manifest": "https://github.com/parvusdomus/tricube/releases/latest/download/system.json",
    "download": "https://github.com/parvusdomus/tricube/releases/latest/download/tricube.zip",
    "license": "LICENSE.txt"
  }